consulk8s.py
consulk8s-0.4.0.dist-info/DESCRIPTION.rst
consulk8s-0.4.0.dist-info/METADATA
consulk8s-0.4.0.dist-info/RECORD
consulk8s-0.4.0.dist-info/WHEEL
consulk8s-0.4.0.dist-info/entry_points.txt
consulk8s-0.4.0.dist-info/metadata.json
consulk8s-0.4.0.dist-info/top_level.txt
