Metadata-Version: 2.0
Name: consulk8s
Version: 0.4.0
Summary: Integrate Consul and Kubernetes
Home-page: https://github.com/joshbenner/consulk8s
Author: Josh Benner
Author-email: joshb@aweber.com
License: BSD
Platform: UNKNOWN
Classifier: Development Status :: 4 - Beta
Classifier: Environment :: Console
Classifier: License :: OSI Approved :: BSD License
Classifier: Intended Audience :: System Administrators
Classifier: Operating System :: OS Independent
Classifier: Programming Language :: Python
Classifier: Programming Language :: Python :: 3.5
Classifier: Programming Language :: Python :: Implementation :: CPython
Classifier: Topic :: Internet :: WWW/HTTP
Classifier: Topic :: System :: Clustering
Classifier: Topic :: System :: Systems Administration
Requires-Dist: click (<8,>=7)
Requires-Dist: kubernetes (<9,>=8)
Provides-Extra: test
Requires-Dist: pytest; extra == 'test'
